durakgame/__init__.py
durakgame/game.py
durakgame/gameutils.py
durakgame/history.py
durakgame/interface.py
durakgame/move.py
durakgame/player.py
durakgame/primitives.py
durakgame-1.0.4.dist-info/METADATA
durakgame-1.0.4.dist-info/WHEEL
durakgame-1.0.4.dist-info/licenses/LICENCE
durakgame-1.0.4.dist-info/RECORD
