Metadata-Version: 2.3
Name: durakgame
Version: 1.0.4
Summary: A simple Durak card game simulator
Project-URL: Github, https://github.com/Artem-Goldenberg/Durak
Author-email: Artem Ibragimov <artem.ibragimov1602@gmail.com>
License-File: LICENCE
Classifier: License :: OSI Approved :: MIT License
Classifier: Operating System :: OS Independent
Classifier: Programming Language :: Python :: 3
Requires-Python: >=3.8
